sshgen/__init__.py
sshgen/__main__.py
sshgen/cli.py
sshgen/generators/model.py
sshgen/generators/sshconfig.py
sshgen/logger.py
sshgen/models/host.py
sshgen/models/loglevel.py
sshgen/models/metafields.py
sshgen/parsers/ansible.py
sshgen/run.py
sshgen/templates/ssh_config.template
sshgen/utils/app.py
sshgen/utils/common.py
sshgen/utils/file.py
sshgen-0.9.0.dist-info/LICENSE
sshgen-0.9.0.dist-info/METADATA
sshgen-0.9.0.dist-info/WHEEL
sshgen-0.9.0.dist-info/entry_points.txt
sshgen-0.9.0.dist-info/RECORD
