Metadata-Version: 2.3
Name: sshgen
Version: 0.9.0
Summary: SSH config generator based on Ansible hosts yaml file
Home-page: https://github.com/pythoninja/sshgen
License: Unlicense
Keywords: ssh,config,ansible,cli,generator
Author: pythoninja
Author-email: pythoninja@users.noreply.github.com
Requires-Python: >=3.12
Classifier: License :: OSI Approved
Classifier: Programming Language :: Python :: 3
Classifier: Programming Language :: Python :: 3.12
Classifier: Programming Language :: Python :: 3.13
Requires-Dist: cyclopts (>=2.4.2,<4.0.0)
Requires-Dist: ruamel-yaml (>=0.17.31,<0.19.0)
Project-URL: Changelog, https://github.com/pythoninja/sshgen/blob/master/CHANGELOG.md
Project-URL: Repository, https://github.com/pythoninja/sshgen
